AcmHelper/__init__.py
AcmHelper/cli/__init__.py
AcmHelper/cli/main.py
AcmHelper/cli/system/__init__.py
AcmHelper/cli/system/config.py
AcmHelper/cli/system/default/checker.py
AcmHelper/cli/system/default/interactor.py
AcmHelper/cli/system/default/template_checker.cpp
AcmHelper/cli/system/default/template_interactor.cpp
AcmHelper/cli/system/default/template_std.cpp
AcmHelper/cli/system/default/template_validator.cpp
AcmHelper/cli/system/default/testlib.h
AcmHelper/cli/system/default/validator.py
AcmHelper/cli/system/main.py
AcmHelper/cli/system/utils.py
AcmHelper/cli/utils.py
AcmHelper/gen/__init__.py
AcmHelper/gen/graph/__init__.py
AcmHelper/gen/graph/base_graph.py
AcmHelper/gen/graph/dag.py
AcmHelper/gen/graph/graph.py
AcmHelper/gen/graph/tree.py
AcmHelper/gen/rand.py
AcmHelper/gen/string.py
acmhelper-0.1.1.dist-info/entry_points.txt
acmhelper-0.1.1.dist-info/WHEEL
acmhelper-0.1.1.dist-info/METADATA
acmhelper-0.1.1.dist-info/RECORD
