Metadata-Version: 2.1
Name: acmhelper
Version: 0.1.1
Summary: The helper for Acmer
License: MIT
Author: CherryGS
Author-email: tickten@outlook.com
Requires-Python: >=3.10,<4.0
Classifier: License :: OSI Approved :: MIT License
Classifier: Programming Language :: Python :: 3
Classifier: Programming Language :: Python :: 3.10
Classifier: Programming Language :: Python :: 3.11
Requires-Dist: loguru (>=0.6.0,<0.7.0)
Requires-Dist: typer[all] (>=0.6.1,<0.7.0)
